regression_testing_framework/__init__.py
regression_testing_framework/celery_app.py
regression_testing_framework/celery_config.py
regression_testing_framework/celery_tasks.py
regression_testing_framework/celeryconfig.py
regression_testing_framework/cli.py
regression_testing_framework/command_generator.py
regression_testing_framework/config_parser.py
regression_testing_framework/database.py
regression_testing_framework/run_tests.py
regression_testing_framework/summary.py
regression_testing_framework/test_runner.py
regression_testing_framework/tasks/__init__.py
regression_testing_framework/tasks/orchestration.py
regression_testing_framework/tasks/test_execution.py
regression_testing_framework/web/__init__.py
regression_testing_framework/web/main.py
regression_testing_framework/web/api/__init__.py
regression_testing_framework/web/api/config.py
regression_testing_framework/web/api/files.py
regression_testing_framework/web/api/jobs.py
regression_testing_framework/web/api/status.py
regression_testing_framework/web/static/style.css
regression_testing_framework/web/templates/dashboard.html
regression_testing_framework/web/templates/files.html
regression_testing_framework/web/templates/job_list.html
regression_testing_framework/web/templates/system_status.html
regression_testing_framework/web/templates/worker_status.html
regression_testing_framework-0.2.0.dist-info/METADATA
regression_testing_framework-0.2.0.dist-info/WHEEL
regression_testing_framework-0.2.0.dist-info/entry_points.txt
regression_testing_framework-0.2.0.dist-info/licenses/LICENSE
regression_testing_framework-0.2.0.dist-info/RECORD
