Metadata-Version: 2.4
Name: regression-testing-framework
Version: 0.2.0
Summary: Run parallel test configurations with log discovery and summary.
Author-email: Nicholas Ballard <nicholaesricballard@gmail.com>
License: MIT License
License-File: LICENSE
Requires-Python: >=3.9
Requires-Dist: celery[redis]>=5.3.0
Requires-Dist: click>=8.1.0
Requires-Dist: flask>=3.1.0
Requires-Dist: pyyaml>=6.0.2
Requires-Dist: sqlite-utils>=3.38
Provides-Extra: dev
Requires-Dist: httpx>=0.24.0; extra == 'dev'
Requires-Dist: pytest-asyncio>=0.21.0; extra == 'dev'
Requires-Dist: pytest>=7.0.0; extra == 'dev'
Provides-Extra: monitoring
Requires-Dist: flower>=2.0.0; extra == 'monitoring'
Provides-Extra: web
Requires-Dist: fastapi>=0.104.0; extra == 'web'
Requires-Dist: jinja2>=3.1.0; extra == 'web'
Requires-Dist: psutil>=5.9.0; extra == 'web'
Requires-Dist: python-multipart>=0.0.6; extra == 'web'
Requires-Dist: uvicorn[standard]>=0.24.0; extra == 'web'
